setup.py
pystruct3/__init__.py
pystruct3/graph.py
pystruct3/list.py
pystruct3/queue.py
pystruct3/stack.py
pystruct3.egg-info/PKG-INFO
pystruct3.egg-info/SOURCES.txt
pystruct3.egg-info/dependency_links.txt
pystruct3.egg-info/not-zip-safe
pystruct3.egg-info/top_level.txt
pystruct3/tests/__init__.py
pystruct3/tests/graph_test.py
pystruct3/tests/list_test.py
pystruct3/tests/queue_test.py
pystruct3/tests/stack_test.py