Metadata-Version: 1.0
Name: pystruct3
Version: 0.1.9
Summary: Algorithms and Data Structures in Python 3
Home-page: https://github.com/ltrottier/pystruct3
Author: Ludovic Trottier
Author-email: ludovic.trottier.2@gmail.com
License: MIT
Platform: UNKNOWN
